<annotation>
	<folder>images</folder>
	<filename>051.png</filename>
	<path>/Users/akhter56/Desktop/Caption Dataset/images/051.png</path>
	<source>
		<database>Unknown</database>
	</source>
	<size>
		<width>1280</width>
		<height>720</height>
		<depth>3</depth>
	</size>
	<segmented>0</segmented>
	<object>
		<name>logo</name>
		<pose>Unspecified</pose>
		<truncated>0</truncated>
		<difficult>0</difficult>
		<bndbox>
			<xmin>38</xmin>
			<ymin>53</ymin>
			<xmax>163</xmax>
			<ymax>106</ymax>
		</bndbox>
	</object>
	<object>
		<name>caption</name>
		<pose>Unspecified</pose>
		<truncated>0</truncated>
		<difficult>0</difficult>
		<bndbox>
			<xmin>165</xmin>
			<ymin>51</ymin>
			<xmax>1119</xmax>
			<ymax>140</ymax>
		</bndbox>
	</object>
	<object>
		<name>logo</name>
		<pose>Unspecified</pose>
		<truncated>0</truncated>
		<difficult>0</difficult>
		<bndbox>
			<xmin>95</xmin>
			<ymin>573</ymin>
			<xmax>211</xmax>
			<ymax>625</ymax>
		</bndbox>
	</object>
	<object>
		<name>current time and temperature</name>
		<pose>Unspecified</pose>
		<truncated>0</truncated>
		<difficult>0</difficult>
		<bndbox>
			<xmin>91</xmin>
			<ymin>628</ymin>
			<xmax>207</xmax>
			<ymax>653</ymax>
		</bndbox>
	</object>
	<object>
		<name>speaker name</name>
		<pose>Unspecified</pose>
		<truncated>0</truncated>
		<difficult>0</difficult>
		<bndbox>
			<xmin>343</xmin>
			<ymin>626</ymin>
			<xmax>679</xmax>
			<ymax>656</ymax>
		</bndbox>
	</object>
	<object>
		<name>discussion topic</name>
		<pose>Unspecified</pose>
		<truncated>0</truncated>
		<difficult>0</difficult>
		<bndbox>
			<xmin>392</xmin>
			<ymin>577</ymin>
			<xmax>893</xmax>
			<ymax>621</ymax>
		</bndbox>
	</object>
	<object>
		<name>scrolling news</name>
		<pose>Unspecified</pose>
		<truncated>1</truncated>
		<difficult>0</difficult>
		<bndbox>
			<xmin>31</xmin>
			<ymin>667</ymin>
			<xmax>1280</xmax>
			<ymax>709</ymax>
		</bndbox>
	</object>
	<object>
		<name>program title</name>
		<pose>Unspecified</pose>
		<truncated>0</truncated>
		<difficult>0</difficult>
		<bndbox>
			<xmin>708</xmin>
			<ymin>628</ymin>
			<xmax>940</xmax>
			<ymax>661</ymax>
		</bndbox>
	</object>
</annotation>
